<?xml version="1.0" encoding="UTF-8"?>
<bundle>
<UIActionBar>
<tooltip>
<ContentNavigation>{crwdns6429263:0}{crwdne6429263:0}</ContentNavigation>
</tooltip>
</UIActionBar>
<UIViewFormTabPane>
<label>
<contentNavigation>{crwdns6429264:0}{crwdne6429264:0}</contentNavigation>
</label>
</UIViewFormTabPane>
<UIPopupWindow>
<title>
<UINavigationForm>{crwdns6429265:0}{crwdne6429265:0}</UINavigationForm>
</title>
</UIPopupWindow>
<PopulateToMenu>
<dialog>
<label>
<id>{crwdns6429266:0}{crwdne6429266:0}</id>
<name>{crwdns6429267:0}{crwdne6429267:0}</name>
<lifecycle>{crwdns6429268:0}{crwdne6429268:0}</lifecycle>
<isDeep>{crwdns6429269:0}{crwdne6429269:0}</isDeep>
<nodetypes>{crwdns6429270:0}{crwdne6429270:0}</nodetypes>
<description>{crwdns6429271:0}{crwdne6429271:0}</description>
<affectedNodeTypeNames>{crwdns6429272:0}{crwdne6429272:0}</affectedNodeTypeNames>
<navigationNode>{crwdns6429273:0}{crwdne6429273:0}</navigationNode>
<index>{crwdns6429274:0}{crwdne6429274:0}</index>
<clickable>{crwdns6429275:0}{crwdne6429275:0}</clickable>
<page>{crwdns6429276:0}{crwdne6429276:0}</page>
<childrenPage>{crwdns6429277:0}{crwdne6429277:0}</childrenPage>
</label>
</dialog>
</PopulateToMenu>
<UINavigationForm>
<label>
<Node>{crwdns6429278:0}{crwdne6429278:0}</Node>
<Visible>{crwdns6429279:0}{crwdne6429279:0}</Visible>
<NavigationNodeInputSet>{crwdns6429280:0}{crwdne6429280:0}</NavigationNodeInputSet>
<Index>{crwdns6429281:0}{crwdne6429281:0}</Index>
<Clickable>{crwdns6429282:0}{crwdne6429282:0}</Clickable>
<NavigationControls>{crwdns6429283:0}{crwdne6429283:0}</NavigationControls>
<ListTargetPageFormInputSet>{crwdns6429284:0}{crwdne6429284:0}</ListTargetPageFormInputSet>
<ListShowCLVByStringInput>{crwdns6429285:0}{crwdne6429285:0}</ListShowCLVByStringInput>
<DetailTargetPageInputSet>{crwdns6429286:0}{crwdne6429286:0}</DetailTargetPageInputSet>
<DetailShowCLVByStringInput>{crwdns6429287:0}{crwdne6429287:0}</DetailShowCLVByStringInput>
<List>{crwdns6429288:0}{crwdne6429288:0}</List>
<Detail>{crwdns6429289:0}{crwdne6429289:0}</Detail>
</label>
<action>
<Save>#{word.save}</Save>
<Cancel>#{word.cancel}</Cancel>
</action>
</UINavigationForm>
<Visible>
<label>
<VisibleEnable>{crwdns6429292:0}{crwdne6429292:0}</VisibleEnable>
<VisibleDisable>{crwdns6429293:0}{crwdne6429293:0}</VisibleDisable>
</label>
</Visible>
<Clickable>
<label>
<ClickableEnable>{crwdns6429294:0}{crwdne6429294:0}</ClickableEnable>
<ClickableDisable>{crwdns6429295:0}{crwdne6429295:0}</ClickableDisable>
</label>
</Clickable>
<NavigationNodeInputSet>
<title>
<SelectNavigationNode>{crwdns6429296:0}{crwdne6429296:0}</SelectNavigationNode>
<RemoveNavigationNode>{crwdns6429297:0}{crwdne6429297:0}</RemoveNavigationNode>
</title>
</NavigationNodeInputSet>
<ListTargetPageFormInputSet>
<title>
<SelectListTargetPage>{crwdns6429298:0}{crwdne6429298:0}</SelectListTargetPage>
<RemoveListTargetPage>{crwdns6429299:0}{crwdne6429299:0}</RemoveListTargetPage>
</title>
</ListTargetPageFormInputSet>
<DetailTargetPageInputSet>
<title>
<SelectDetailTargetPage>{crwdns6429300:0}{crwdne6429300:0}</SelectDetailTargetPage>
<RemoveDetailTargetPage>{crwdns6429301:0}{crwdne6429301:0}</RemoveDetailTargetPage>
</title>
</DetailTargetPageInputSet>
<NavigationSelectorPopupWindow>
<title>
<UINavigationSelector>{crwdns6429302:0}{crwdne6429302:0}</UINavigationSelector>
</title>
</NavigationSelectorPopupWindow>
<ListTargetPageSelectorPopupWindow>
<title>
<UIPageSelector>{crwdns6429303:0}{crwdne6429303:0}</UIPageSelector>
</title>
</ListTargetPageSelectorPopupWindow>
<DetailTargetPageSelectorPopupWindow>
<title>
<UIPageSelector>{crwdns6429304:0}{crwdne6429304:0}</UIPageSelector>
</title>
</DetailTargetPageSelectorPopupWindow>
</bundle>
